vanityonionr/__init__.py
vanityonionr-0.0.0.dist-info/LICENSE
vanityonionr-0.0.0.dist-info/METADATA
vanityonionr-0.0.0.dist-info/WHEEL
vanityonionr-0.0.0.dist-info/top_level.txt
vanityonionr-0.0.0.dist-info/RECORD
