Metadata-Version: 2.1
Name: vanityonionr
Version: 0.0.0
Summary: Generate vanity keys for Onionr
Home-page: https://github.com/beardog108/vanity-onionr/
Author: Kevin Froman
Author-email: beardog@mailbox.org
License: UNKNOWN
Platform: UNKNOWN
Classifier: Programming Language :: Python :: 3
Classifier: License :: OSI Approved :: GNU General Public License v3 (GPLv3)
Classifier: Operating System :: OS Independent
Requires-Dist: mnemonic (>=0.18)
Requires-Dist: PyNaCl (>=1.3.0)
